<?xml version="1.0" encoding="UTF-8"?>
<fb version="0.4.0" size="5438">
  <f>
    <added t="I">8</added>
    <cycles t="I">5</cycles>
    <error>
      <v t="S">GET https://api.github.com/users/objectionary/repos?per_page=100: 403 - API rate limit exceeded for site ID installation. If you reach out to GitHub Support for help, please include the request ID 5A80:33B6AC:107F689D:10A2BC68:66D9AD64 and timestamp 2024-09-05 13:08:52 UTC. // See: https://docs.github.com/rest/overview/rate-limits-for-the-rest-api</v>
      <v t="S">GET https://api.github.com/users/objectionary/repos?per_page=100: 403 - API rate limit exceeded for site ID installation. If you reach out to GitHub Support for help, please include the request ID 5A80:33B6AC:10806BE2:10A3C180:66D9ADA1 and timestamp 2024-09-05 13:09:53 UTC. // See: https://docs.github.com/rest/overview/rate-limits-for-the-rest-api</v>
      <v t="S">GET https://api.github.com/users/objectionary/repos?per_page=100: 403 - API rate limit exceeded for site ID installation. If you reach out to GitHub Support for help, please include the request ID 5A80:33B6AC:1081637B:10A4BADD:66D9ADDE and timestamp 2024-09-05 13:10:54 UTC. // See: https://docs.github.com/rest/overview/rate-limits-for-the-rest-api</v>
      <v t="S">GET https://api.github.com/users/objectionary/repos?per_page=100: 403 - API rate limit exceeded for site ID installation. If you reach out to GitHub Support for help, please include the request ID 5A80:33B6AC:10825AA1:10A5B405:66D9AE1B and timestamp 2024-09-05 13:11:55 UTC. // See: https://docs.github.com/rest/overview/rate-limits-for-the-rest-api</v>
      <v t="S">GET https://api.github.com/users/objectionary/repos?per_page=100: 403 - API rate limit exceeded for site ID installation. If you reach out to GitHub Support for help, please include the request ID 5A80:33B6AC:10834B79:10A6A6CB:66D9AE58 and timestamp 2024-09-05 13:12:56 UTC. // See: https://docs.github.com/rest/overview/rate-limits-for-the-rest-api</v>
      <v t="S">GET https://api.github.com/users/objectionary/repos?per_page=100: 403 - API rate limit exceeded for site ID installation. If you reach out to GitHub Support for help, please include the request ID 5A80:33B6AC:10843111:10A78E15:66D9AE94 and timestamp 2024-09-05 13:13:57 UTC. // See: https://docs.github.com/rest/overview/rate-limits-for-the-rest-api</v>
      <v t="S">GET https://api.github.com/users/objectionary/repos?per_page=100: 403 - API rate limit exceeded for site ID installation. If you reach out to GitHub Support for help, please include the request ID 5A80:33B6AC:10851D4E:10A87C35:66D9AED1 and timestamp 2024-09-05 13:14:57 UTC. // See: https://docs.github.com/rest/overview/rate-limits-for-the-rest-api</v>
      <v t="S">GET https://api.github.com/users/objectionary/repos?per_page=100: 403 - API rate limit exceeded for site ID installation. If you reach out to GitHub Support for help, please include the request ID 5A80:33B6AC:1086067F:10A9673D:66D9AF0E and timestamp 2024-09-05 13:15:58 UTC. // See: https://docs.github.com/rest/overview/rate-limits-for-the-rest-api</v>
      <v t="S">GET https://api.github.com/users/objectionary/repos?per_page=100: 403 - API rate limit exceeded for site ID installation. If you reach out to GitHub Support for help, please include the request ID 5A80:33B6AC:1086F0A1:10AA5362:66D9AF4B and timestamp 2024-09-05 13:16:59 UTC. // See: https://docs.github.com/rest/overview/rate-limits-for-the-rest-api</v>
      <v t="S">GET https://api.github.com/users/objectionary/repos?per_page=100: 403 - API rate limit exceeded for site ID installation. If you reach out to GitHub Support for help, please include the request ID 5A80:33B6AC:1087D608:10AB3AA3:66D9AF88 and timestamp 2024-09-05 13:18:00 UTC. // See: https://docs.github.com/rest/overview/rate-limits-for-the-rest-api</v>
      <v t="S">GET https://api.github.com/users/objectionary/repos?per_page=100: 403 - API rate limit exceeded for site ID installation. If you reach out to GitHub Support for help, please include the request ID 5A80:33B6AC:1088C1A3:10AC283F:66D9AFC5 and timestamp 2024-09-05 13:19:01 UTC. // See: https://docs.github.com/rest/overview/rate-limits-for-the-rest-api</v>
      <v t="S">GET https://api.github.com/users/objectionary/repos?per_page=100: 403 - API rate limit exceeded for site ID installation. If you reach out to GitHub Support for help, please include the request ID 5A80:33B6AC:1089AE93:10AD16F7:66D9B002 and timestamp 2024-09-05 13:20:02 UTC. // See: https://docs.github.com/rest/overview/rate-limits-for-the-rest-api</v>
      <v t="S">GET https://api.github.com/users/objectionary/repos?per_page=100: 403 - API rate limit exceeded for site ID installation. If you reach out to GitHub Support for help, please include the request ID 5A80:33B6AC:108AAF20:10AE1956:66D9B03F and timestamp 2024-09-05 13:21:03 UTC. // See: https://docs.github.com/rest/overview/rate-limits-for-the-rest-api</v>
    </error>
    <removed t="I">8</removed>
    <seconds t="F">792.857861419</seconds>
    <version t="S">0.25.2</version>
    <what t="S">judges-summary</what>
    <when t="T">2024-09-05T13:21:03Z</when>
  </f>
  <f>
    <_id t="I">1</_id>
    <_time t="T">2024-09-05T13:07:51Z</_time>
    <_version t="S">0.4.0/0.25.2/</_version>
    <what t="S">dimensions-of-terrain</what>
    <when t="T">2024-09-05T13:07:51Z</when>
  </f>
  <f>
    <_id t="I">2</_id>
    <_time t="T">2024-09-05T13:10:54Z</_time>
    <_version t="S">0.4.0/0.25.2/</_version>
    <since t="T">2024-08-08T13:10:54Z</since>
    <what t="S">quality-of-service</what>
    <when t="T">2024-09-05T13:10:54Z</when>
  </f>
  <f>
    <_id t="I">3</_id>
    <_time t="T">2024-09-05T13:11:55Z</_time>
    <_version t="S">0.4.0/0.25.2/</_version>
    <since t="T">2024-08-08T13:11:55Z</since>
    <what t="S">quantity-of-deliverables</what>
    <when t="T">2024-09-05T13:11:55Z</when>
  </f>
</fb>
