<?xml version="1.0" encoding="UTF-8"?>
<fb version="0.4.0" size="5387">
  <f>
    <added t="I">8</added>
    <cycles t="I">5</cycles>
    <error>
      <v t="S">GET https://api.github.com/users/objectionary/repos?per_page=100: 403 - API rate limit exceeded for site ID installation. If you reach out to GitHub Support for help, please include the request ID C7C0:3BF7FE:6AEECA:C8C9B8:66D29B46 and timestamp 2024-08-31 04:25:42 UTC. // See: https://docs.github.com/rest/overview/rate-limits-for-the-rest-api</v>
      <v t="S">GET https://api.github.com/users/objectionary/repos?per_page=100: 403 - API rate limit exceeded for site ID installation. If you reach out to GitHub Support for help, please include the request ID C7C0:EE004:564587:A18DE2:66D29B83 and timestamp 2024-08-31 04:26:43 UTC. // See: https://docs.github.com/rest/overview/rate-limits-for-the-rest-api</v>
      <v t="S">GET https://api.github.com/users/objectionary/repos?per_page=100: 403 - API rate limit exceeded for site ID installation. If you reach out to GitHub Support for help, please include the request ID C7C0:12DE33:5A5EED:A9BA30:66D29BBF and timestamp 2024-08-31 04:27:43 UTC. // See: https://docs.github.com/rest/overview/rate-limits-for-the-rest-api</v>
      <v t="S">GET https://api.github.com/users/objectionary/repos?per_page=100: 403 - API rate limit exceeded for site ID installation. If you reach out to GitHub Support for help, please include the request ID C7C0:EE004:57781F:A3D5B1:66D29BFB and timestamp 2024-08-31 04:28:44 UTC. // See: https://docs.github.com/rest/overview/rate-limits-for-the-rest-api</v>
      <v t="S">GET https://api.github.com/users/objectionary/repos?per_page=100: 403 - API rate limit exceeded for site ID installation. If you reach out to GitHub Support for help, please include the request ID C7C0:12DE33:5B675C:ABAF74:66D29C38 and timestamp 2024-08-31 04:29:44 UTC. // See: https://docs.github.com/rest/overview/rate-limits-for-the-rest-api</v>
      <v t="S">GET https://api.github.com/users/objectionary/repos?per_page=100: 403 - API rate limit exceeded for site ID installation. If you reach out to GitHub Support for help, please include the request ID C7C0:12DE33:5BED90:ACAE21:66D29C74 and timestamp 2024-08-31 04:30:44 UTC. // See: https://docs.github.com/rest/overview/rate-limits-for-the-rest-api</v>
      <v t="S">GET https://api.github.com/users/objectionary/repos?per_page=100: 403 - API rate limit exceeded for site ID installation. If you reach out to GitHub Support for help, please include the request ID C7C0:EE004:594D0D:A75487:66D29CB1 and timestamp 2024-08-31 04:31:45 UTC. // See: https://docs.github.com/rest/overview/rate-limits-for-the-rest-api</v>
      <v t="S">GET https://api.github.com/users/objectionary/repos?per_page=100: 403 - API rate limit exceeded for site ID installation. If you reach out to GitHub Support for help, please include the request ID C7C0:12DE33:5CF302:AE9CB9:66D29CED and timestamp 2024-08-31 04:32:45 UTC. // See: https://docs.github.com/rest/overview/rate-limits-for-the-rest-api</v>
      <v t="S">GET https://api.github.com/users/objectionary/repos?per_page=100: 403 - API rate limit exceeded for site ID installation. If you reach out to GitHub Support for help, please include the request ID C7C0:3BF7FE:7041E9:D2EEF5:66D29D29 and timestamp 2024-08-31 04:33:45 UTC. // See: https://docs.github.com/rest/overview/rate-limits-for-the-rest-api</v>
      <v t="S">GET https://api.github.com/users/objectionary/repos?per_page=100: 403 - API rate limit exceeded for site ID installation. If you reach out to GitHub Support for help, please include the request ID C7C0:EE004:5B167F:AABB6E:66D29D66 and timestamp 2024-08-31 04:34:46 UTC. // See: https://docs.github.com/rest/overview/rate-limits-for-the-rest-api</v>
      <v t="S">GET https://api.github.com/users/objectionary/repos?per_page=100: 403 - API rate limit exceeded for site ID installation. If you reach out to GitHub Support for help, please include the request ID C7C0:3BF7FE:7188A2:D55E8A:66D29DA2 and timestamp 2024-08-31 04:35:46 UTC. // See: https://docs.github.com/rest/overview/rate-limits-for-the-rest-api</v>
      <v t="S">GET https://api.github.com/users/objectionary/repos?per_page=100: 403 - API rate limit exceeded for site ID installation. If you reach out to GitHub Support for help, please include the request ID C7C0:3BF7FE:722DE4:D69A8E:66D29DDF and timestamp 2024-08-31 04:36:47 UTC. // See: https://docs.github.com/rest/overview/rate-limits-for-the-rest-api</v>
      <v t="S">GET https://api.github.com/users/objectionary/repos?per_page=100: 403 - API rate limit exceeded for site ID installation. If you reach out to GitHub Support for help, please include the request ID C7C0:12DE33:5F8B1F:B38922:66D29E1B and timestamp 2024-08-31 04:37:47 UTC. // See: https://docs.github.com/rest/overview/rate-limits-for-the-rest-api</v>
    </error>
    <removed t="I">8</removed>
    <seconds t="F">785.335500315</seconds>
    <version t="S">0.25.2</version>
    <what t="S">judges-summary</what>
    <when t="T">2024-08-31T04:37:47Z</when>
  </f>
  <f>
    <_id t="I">1</_id>
    <_time t="T">2024-08-31T04:24:42Z</_time>
    <_version t="S">0.4.0/0.25.2/</_version>
    <what t="S">dimensions-of-terrain</what>
    <when t="T">2024-08-31T04:24:42Z</when>
  </f>
  <f>
    <_id t="I">2</_id>
    <_time t="T">2024-08-31T04:27:43Z</_time>
    <_version t="S">0.4.0/0.25.2/</_version>
    <since t="T">2024-08-03T04:27:43Z</since>
    <what t="S">quality-of-service</what>
    <when t="T">2024-08-31T04:27:43Z</when>
  </f>
  <f>
    <_id t="I">3</_id>
    <_time t="T">2024-08-31T04:28:44Z</_time>
    <_version t="S">0.4.0/0.25.2/</_version>
    <since t="T">2024-08-03T04:28:44Z</since>
    <what t="S">quantity-of-deliverables</what>
    <when t="T">2024-08-31T04:28:44Z</when>
  </f>
</fb>
